BrokenDotmap/__init__.py
BrokenDotmap/BaseLoader.py
BrokenDotmap/BrokenDotmap.py
BrokenDotmap/Loaders/__init__.py
BrokenDotmap/Loaders/LoaderPIL.py
BrokenDotmap/Loaders/LoaderTOML.py
broken_dotmap-2024.1.15.dist-info/License.md
broken_dotmap-2024.1.15.dist-info/METADATA
broken_dotmap-2024.1.15.dist-info/WHEEL
broken_dotmap-2024.1.15.dist-info/RECORD
