Metadata-Version: 2.1
Name: broken-dotmap
Version: 2024.1.15
Summary: A database-less, smart dotmap for normal dictionary usage or disk-synced plain data
Home-page: https://github.com/BrokenSource/BrokenDotmap
License: MIT
Author: Tremeschin
Author-email: tremeschin@users.noreply.github.com
Requires-Python: >=3.10,<3.13
Classifier: License :: OSI Approved :: MIT License
Classifier: Programming Language :: Python :: 3
Classifier: Programming Language :: Python :: 3.10
Classifier: Programming Language :: Python :: 3.11
Classifier: Programming Language :: Python :: 3.12
Provides-Extra: all
Provides-Extra: imageio
Provides-Extra: numpy
Provides-Extra: pillow
Provides-Extra: requests
Provides-Extra: requests-cache
Provides-Extra: rich
Provides-Extra: toml
Provides-Extra: ujson
Provides-Extra: yaml
Provides-Extra: yt-dlp
Requires-Dist: attrs (>=23.2.0,<24.0.0)
Requires-Dist: imageio (>=2.33.1,<3.0.0) ; extra == "all" or extra == "imageio"
Requires-Dist: numpy (>=1.26.3,<2.0.0) ; extra == "all" or extra == "numpy"
Requires-Dist: pillow (>=10.2.0,<11.0.0) ; extra == "all" or extra == "pillow"
Requires-Dist: pyyaml (>=6.0.1,<7.0.0) ; extra == "all" or extra == "yaml"
Requires-Dist: requests (>=2.31.0,<3.0.0) ; extra == "all" or extra == "requests"
Requires-Dist: requests-cache (>=1.1.1,<2.0.0) ; extra == "all" or extra == "requests-cache"
Requires-Dist: rich (>=13.7.0,<14.0.0) ; extra == "all" or extra == "rich"
Requires-Dist: toml (>=0.10.2,<0.11.0) ; extra == "all" or extra == "toml"
Requires-Dist: ujson (>=5.9.0,<6.0.0) ; extra == "all" or extra == "ujson"
Requires-Dist: validators (>=0.22.0,<0.23.0)
Requires-Dist: yt-dlp (>=2023.12.30,<2024.0.0)
Project-URL: Documentation, https://github.com/BrokenSource/BrokenDotmap
Project-URL: Repository, https://github.com/BrokenSource/BrokenDotmap
